setup.py
ymci_ext_oauth/__init__.py
ymci_ext_oauth/db.py
ymci_ext_oauth/form.py
ymci_ext_oauth/hooks.py
ymci_ext_oauth/routes.py
ymci_ext_oauth.egg-info/PKG-INFO
ymci_ext_oauth.egg-info/SOURCES.txt
ymci_ext_oauth.egg-info/dependency_links.txt
ymci_ext_oauth.egg-info/entry_points.txt
ymci_ext_oauth.egg-info/top_level.txt
ymci_ext_oauth/templates/blocks
ymci_ext_oauth/templates/index.html