Metadata-Version: 1.1
Name: ymci-ext-oauth
Version: 1.0
Summary: OAuth plugin for ymci
Home-page: UNKNOWN
Author: Florian Mounier, Kozea
Author-email: florian.mounier@kozea.fr
License: UNKNOWN
Platform: Any
Provides: ymci_ext_oauth
